qupled/__init__.py
qupled/database.py
qupled/dimension.py
qupled/esa.py
qupled/hf.py
qupled/mpi.py
qupled/native.cpython-311-aarch64-linux-gnu.so
qupled/output.py
qupled/qstls.py
qupled/qstlsiet.py
qupled/qvsstls.py
qupled/rpa.py
qupled/serialize.py
qupled/stls.py
qupled/stlsiet.py
qupled/timer.py
qupled/vsstls.py
qupled.libs/libgomp-947d5fa1.so.1.0.0
qupled.libs/libgsl-f7298b36.so.23.1.0
qupled.libs/libgslcblas-cf1da87e.so.0.0.0
qupled-1.4.1.dist-info/METADATA
qupled-1.4.1.dist-info/WHEEL
qupled-1.4.1.dist-info/top_level.txt
qupled-1.4.1.dist-info/RECORD
qupled-1.4.1.dist-info/licenses/LICENSE
