Metadata-Version: 2.4
Name: qupled
Version: 1.4.1
Summary: qupled: a package to investigate quantum plasmas via the dielectric formalism
Author-email: Federico Lucco Castello <federico.luccocastello@gmail.com>
License-Expression: GPL-3.0-or-later
Classifier: Programming Language :: Python :: 3.10
Classifier: Operating System :: MacOS
Classifier: Operating System :: POSIX :: Linux
Requires-Python: <3.14,>=3.10
License-File: LICENSE
Requires-Dist: blosc2~=3.2
Requires-Dist: matplotlib~=3.7
Requires-Dist: numpy<2.0
Requires-Dist: SQLAlchemy~=2.0
Provides-Extra: testing
Requires-Dist: pytest~=8.0; extra == "testing"
Requires-Dist: pytest-mock~=3.12; extra == "testing"
Provides-Extra: docs
Requires-Dist: sphinx-rtd-theme~=2.0.0; extra == "docs"
Requires-Dist: sphinxcontrib-applehelp~=2.0.0; extra == "docs"
Requires-Dist: sphinxcontrib-devhelp~=2.0.0; extra == "docs"
Requires-Dist: sphinxcontrib-htmlhelp~=2.1.0; extra == "docs"
Requires-Dist: sphinxcontrib-jquery~=4.1; extra == "docs"
Requires-Dist: sphinxcontrib-jsmath~=1.0.1; extra == "docs"
Requires-Dist: sphinxcontrib-qthelp~=2.0.0; extra == "docs"
Requires-Dist: sphinxcontrib-serializinghtml~=2.0.0; extra == "docs"
Dynamic: license-file
